netbox_contextmenus/__init__.py
netbox_contextmenus/middleware.py
netbox_contextmenus/pluginvars.py
netbox_contextmenus/urls.py
netbox_contextmenus/views.py
netbox_contextmenus/templates/netbox_contextmenus/nbcm.js
netbox_contextmenus-1.4.13.dist-info/licenses/LICENSE
netbox_contextmenus-1.4.13.dist-info/METADATA
netbox_contextmenus-1.4.13.dist-info/WHEEL
netbox_contextmenus-1.4.13.dist-info/top_level.txt
netbox_contextmenus-1.4.13.dist-info/RECORD
