Metadata-Version: 2.4
Name: netbox_contextmenus
Version: 1.4.13
Summary: Add context menu to links in NetBox
Home-page: https://github.com/PieterL75/netbox_contextmenus
Author: Pieter Lambrecht
Author-email: pieter.lambrecht@gmail.com
Classifier: Development Status :: 2 - Pre-Alpha
Classifier: Framework :: Django
Classifier: Programming Language :: Python :: 3
License-File: LICENSE
Dynamic: author
Dynamic: author-email
Dynamic: classifier
Dynamic: description
Dynamic: description-content-type
Dynamic: home-page
Dynamic: license-file
Dynamic: summary
